tailwind_py/__init__.py
tailwind_py/cli.py
tailwind_py/download.py
tailwind_py/tailwind.py
tailwind_py-0.1.4.dist-info/LICENSE
tailwind_py-0.1.4.dist-info/METADATA
tailwind_py-0.1.4.dist-info/WHEEL
tailwind_py-0.1.4.dist-info/entry_points.txt
tailwind_py-0.1.4.dist-info/RECORD
