Metadata-Version: 2.3
Name: tailwind-py
Version: 0.1.4
Summary: Install Tailwind CSS in Python projects, no NPM required.
License: Apache-2.0
Keywords: frontend,utils,css,tailwind
Author: Shadi Boomi
Author-email: <shadi.boomi@gmail.com>
Requires-Python: >=3.12
Classifier: Programming Language :: Python :: 3.12
Classifier: Topic :: Software Development :: Build Tools
Classifier: Topic :: Software Development :: Libraries :: Python Modules
Classifier: Topic :: Internet :: WWW/HTTP :: Dynamic Content :: CGI Tools/Libraries
Requires-Dist: requests (>=2.32.3,<3.0.0)
Project-URL: Repository, https://github.com/sboomi/tailwind-py
